python_magi/__init__.py
python_magi/magi.py
python_magi/.ipynb_checkpoints/Untitled-checkpoint.ipynb
python_magi-0.0.4.dist-info/METADATA
python_magi-0.0.4.dist-info/WHEEL
python_magi-0.0.4.dist-info/licenses/LICENSE
python_magi-0.0.4.dist-info/RECORD
