Metadata-Version: 2.4
Name: python_magi
Version: 0.0.4
Summary: Python-MAGI: A TensorFlow Probability-Powered Upgraded Implementation of MAnifold-Constrained Gaussian Process Inference (MAGI)
Project-URL: Homepage, https://github.com/skbwu/Python-MAGI
Project-URL: Documentation, https://github.com/skbwu/Python-MAGI/README.md
Project-URL: Issues, https://github.com/skbwu/Python-MAGI/issues
Author-email: Skyler Wu <skylerw@stanford.edu>, Samuel Kou <kou@stat.harvard.edu>, Shihao Yang <shihao.yang@isye.gatech.edu>
Maintainer-email: Skyler Wu <skylerw@stanford.edu>
License-Expression: GPL-3.0-or-later
License-File: LICENSE
Keywords: dynamical systems,inverse problems,monte carlo
Classifier: Development Status :: 3 - Alpha
Classifier: Operating System :: OS Independent
Classifier: Programming Language :: Python :: 3
Requires-Python: >=3.8
Requires-Dist: numpy>=1.26.4
Requires-Dist: scikit-learn>=1.5.2
Requires-Dist: scipy>=1.11.4
Requires-Dist: tensorflow-probability>=0.25.0
Requires-Dist: tensorflow>=2.18.0
Requires-Dist: tf-keras>=2.18.0
Requires-Dist: tqdm>=4.66.5
